pylibsrd/__init__.py
pylibsrd/__version__.py
pylibsrd/htmlbuilder.py
pylibsrd/image_convert.py
pylibsrd/markhtml.py
pylibsrd/merge_pdf.py
pylibsrd/pdf_resizer.py
pylibsrd/table.py
pylibsrd-1.3.4.dist-info/licenses/LICENSE
pylibsrd-1.3.4.dist-info/METADATA
pylibsrd-1.3.4.dist-info/WHEEL
pylibsrd-1.3.4.dist-info/entry_points.txt
pylibsrd-1.3.4.dist-info/top_level.txt
pylibsrd-1.3.4.dist-info/RECORD
