Metadata-Version: 2.4
Name: pylibsrd
Version: 1.3.4
Summary: pylibSrd is a library containing my modules I use repeatedly.
Home-page: https://github.com/Samdavis112/pylibsrd
Author: Sam Davis
Author-email: srd076@icloud.com
License-File: LICENSE
Requires-Dist: pillow
Requires-Dist: tabulate
Requires-Dist: pypdf
Dynamic: author
Dynamic: author-email
Dynamic: description
Dynamic: home-page
Dynamic: license-file
Dynamic: requires-dist
Dynamic: summary
